Products.CMFDiffTool-4.0.5-py3.13-nspkg.pth
Products/CMFDiffTool/BaseDiff.py
Products/CMFDiffTool/BinaryDiff.py
Products/CMFDiffTool/CMFDTHtmlDiff.py
Products/CMFDiffTool/CMFDiffTool.py
Products/CMFDiffTool/ChangeSet.py
Products/CMFDiffTool/FieldDiff.py
Products/CMFDiffTool/ListDiff.py
Products/CMFDiffTool/TextDiff.py
Products/CMFDiffTool/__init__.py
Products/CMFDiffTool/choicediff.py
Products/CMFDiffTool/configure.zcml
Products/CMFDiffTool/dexteritydiff.py
Products/CMFDiffTool/namedfile.py
Products/CMFDiffTool/profiles.zcml
Products/CMFDiffTool/testing.py
Products/CMFDiffTool/tool.gif
Products/CMFDiffTool/utils.py
Products/CMFDiffTool/exportimport/__init__.py
Products/CMFDiffTool/exportimport/configure.zcml
Products/CMFDiffTool/exportimport/difftool.py
Products/CMFDiffTool/interfaces/IChangeSet.py
Products/CMFDiffTool/interfaces/__init__.py
Products/CMFDiffTool/interfaces/portal_diff.py
Products/CMFDiffTool/libs/__init__.py
Products/CMFDiffTool/libs/htmldiff.py
Products/CMFDiffTool/profiles/default/componentregistry.xml
Products/CMFDiffTool/profiles/default/metadata.xml
Products/CMFDiffTool/tests/BaseTestCase.py
Products/CMFDiffTool/tests/__init__.py
Products/CMFDiffTool/tests/testChangeSet.py
Products/CMFDiffTool/tests/testDiffTool.py
Products/CMFDiffTool/tests/testFieldDiff.py
Products/CMFDiffTool/tests/testListDiff.py
Products/CMFDiffTool/tests/testTextDiff.py
Products/CMFDiffTool/tests/test_astextdiff.py
Products/CMFDiffTool/tests/test_binarydiff.py
Products/CMFDiffTool/tests/test_choicediff.py
Products/CMFDiffTool/tests/test_dexteritydiff.py
Products/CMFDiffTool/tests/test_filelistdiff.py
Products/CMFDiffTool/tests/test_install.py
Products/CMFDiffTool/tests/test_richtextdiff.py
Products/CMFDiffTool/zpt/editCMFDiffTool.zpt
products_cmfdifftool-4.0.5.dist-info/METADATA
products_cmfdifftool-4.0.5.dist-info/WHEEL
products_cmfdifftool-4.0.5.dist-info/entry_points.txt
products_cmfdifftool-4.0.5.dist-info/namespace_packages.txt
products_cmfdifftool-4.0.5.dist-info/top_level.txt
products_cmfdifftool-4.0.5.dist-info/RECORD
