Metadata-Version: 2.2
Name: Products.CMFDiffTool
Version: 4.0.5
Summary: Diff tool for Plone
Home-page: https://github.com/plone/Products.CMFDiffTool
Author: Brent Hendricks
Author-email: plone-developers@lists.sourceforge.net
License: GPL
Keywords: Diff Plone
Classifier: Development Status :: 5 - Production/Stable
Classifier: Programming Language :: Python :: 3.8
Classifier: Programming Language :: Python :: 3.9
Classifier: Programming Language :: Python :: 3.10
Classifier: Programming Language :: Python :: 3.11
Classifier: Programming Language :: Python :: 3.12
Classifier: Framework :: Plone
Classifier: Framework :: Plone :: 6.0
Classifier: Framework :: Plone :: 6.1
Classifier: Framework :: Plone :: Core
Classifier: License :: OSI Approved :: GNU General Public License (GPL)
Classifier: Topic :: Internet :: WWW/HTTP
Requires-Python: >=3.8
Requires-Dist: Products.GenericSetup
Requires-Dist: Products.PortalTransforms
Requires-Dist: Zope
Requires-Dist: setuptools
Requires-Dist: plone.base
Requires-Dist: z3c.relationfield
Provides-Extra: test
Requires-Dist: plone.app.testing; extra == "test"
Requires-Dist: plone.namedfile; extra == "test"
Requires-Dist: plone.app.contenttypes[test]; extra == "test"
Requires-Dist: zope.intid; extra == "test"
Dynamic: author
Dynamic: author-email
Dynamic: classifier
Dynamic: description
Dynamic: description-content-type
Dynamic: home-page
Dynamic: keywords
Dynamic: license
Dynamic: provides-extra
Dynamic: requires-dist
Dynamic: requires-python
Dynamic: summary
